ndex2/NetworkQuery.py
ndex2/NiceCXBuilder.py
ndex2/__init__.py
ndex2/client.py
ndex2/create_aspect.py
ndex2/networkn.py
ndex2/test/__init__.py
ndex2/test/non_unittest_testing.py
ndex2/test/scratch_test_networkn.py
ndex2/test/scratchtests.py
ndex2/test/test_NdexClient.py
ndex2/test/test_NetworkNConstructor.py
ndex2/test/test_ProvenanceAndProfile.py
ndex2/test/test_UpdatingNsetProperty.py
ndex2/test/test_network.py
ndex2/test/test_networkn.py
ndex2/test/test_properties.py
ndex2/test/test_query.py
ndex2/test/test_setting_visibility.py
ndex2/test/test_system_properties.py
ndex2/test/test_user.py
nicecxModel/NiceCXNetwork.py
nicecxModel/NiceCXStreamer.py
nicecxModel/__init__.py
nicecxModel/cx/__init__.py
nicecxModel/cx/aspects/AspectElement.py
nicecxModel/cx/aspects/AttributeCommon.py
nicecxModel/cx/aspects/CXSimpleAttribute.py
nicecxModel/cx/aspects/CitationCommon.py
nicecxModel/cx/aspects/CitationElement.py
nicecxModel/cx/aspects/DataModelsUtil.py
nicecxModel/cx/aspects/EdgeAttributesElement.py
nicecxModel/cx/aspects/EdgesElement.py
nicecxModel/cx/aspects/NameSpaces.py
nicecxModel/cx/aspects/NetworkAttributesElement.py
nicecxModel/cx/aspects/NodeAttributesElement.py
nicecxModel/cx/aspects/NodesElement.py
nicecxModel/cx/aspects/SimpleNode.py
nicecxModel/cx/aspects/SupportElement.py
nicecxModel/cx/aspects/__init__.py
nicecxModel/metadata/MetaDataElement.py
nicecxModel/metadata/__init__.py
nicecxModel/tests/__init__.py
nicecxModel/tests/fast_test1.py
nicecxModel/tests/test_load_network.py
nicecxModel/tests/test_loading_by_aspects.py
nicecx_dev-0.0.1b7.dist-info/DESCRIPTION.rst
nicecx_dev-0.0.1b7.dist-info/METADATA
nicecx_dev-0.0.1b7.dist-info/RECORD
nicecx_dev-0.0.1b7.dist-info/WHEEL
nicecx_dev-0.0.1b7.dist-info/metadata.json
nicecx_dev-0.0.1b7.dist-info/top_level.txt
